datasette_rewrite_sql/__init__.py
datasette_rewrite_sql/hookspecs.py
datasette_rewrite_sql-0.1.dist-info/LICENSE
datasette_rewrite_sql-0.1.dist-info/METADATA
datasette_rewrite_sql-0.1.dist-info/WHEEL
datasette_rewrite_sql-0.1.dist-info/entry_points.txt
datasette_rewrite_sql-0.1.dist-info/top_level.txt
datasette_rewrite_sql-0.1.dist-info/RECORD
