Metadata-Version: 2.1
Name: datasette-rewrite-sql
Version: 0.1
Summary: Adds a rewrite_sql hook to Datasette
Home-page: https://github.com/cldellow/datasette-rewrite-sql
Author: Colin Dellow
License: Apache License, Version 2.0
Project-URL: Issues, https://github.com/cldellow/datasette-rewrite-sql/issues
Project-URL: CI, https://github.com/cldellow/datasette-rewrite-sql/actions
Project-URL: Changelog, https://github.com/cldellow/datasette-rewrite-sql/releases
Classifier: Framework :: Datasette
Classifier: License :: OSI Approved :: Apache Software License
Requires-Python: >=3.7
License-File: LICENSE
Requires-Dist: datasette
Provides-Extra: test
Requires-Dist: pytest ; extra == 'test'
Requires-Dist: pytest-asyncio ; extra == 'test'
Requires-Dist: pytest-watch ; extra == 'test'
